[
  {
    "played": 2,
    "won": 2,
    "drawn": 0,
    "lost": 0,
    "points": 6,
    "goalFor": 3,
    "goalAgainst": 1,
    "goalDifference": 2,
    "team": "Chelsea FC"
  },
  {
    "played": 2,
    "won": 2,
    "drawn": 0,
    "lost": 0,
    "points": 6,
    "goalFor": 3,
    "goalAgainst": 1,
    "goalDifference": 2,
    "team": "FC Bayern"
  },
  {
    "played": 2,
    "won": 1,
    "drawn": 1,
    "lost": 0,
    "points": 4,
    "goalFor": 5,
    "goalAgainst": 2,
    "goalDifference": 3,
    "team": "Atlético de Madrid"
  },
  {
    "played": 2,
    "won": 1,
    "drawn": 0,
    "lost": 1,
    "points": 3,
    "goalFor": 6,
    "goalAgainst": 2,
    "goalDifference": 4,
    "team": "Manchester United FC"
  },
  {
    "played": 1,
    "won": 1,
    "drawn": 0,
    "lost": 0,
    "points": 3,
    "goalFor": 3,
    "goalAgainst": 0,
    "goalDifference": 3,
    "team": "Real Madrid CF"
  },
  {
    "played": 2,
    "won": 1,
    "drawn": 0,
    "lost": 1,
    "points": 3,
    "goalFor": 2,
    "goalAgainst": 2,
    "goalDifference": 0,
    "team": "Juventus FC"
  },
  {
    "played": 2,
    "won": 1,
    "drawn": 0,
    "lost": 1,
    "points": 3,
    "goalFor": 2,
    "goalAgainst": 4,
    "goalDifference": -2,
    "team": "Manchester City FC"
  },
  {
    "played": 1,
    "won": 0,
    "drawn": 1,
    "lost": 0,
    "points": 1,
    "goalFor": 1,
    "goalAgainst": 1,
    "goalDifference": 0,
    "team": "Athletic de Bilbao"
  },
  {
    "played": 2,
    "won": 0,
    "drawn": 1,
    "lost": 1,
    "points": 1,
    "goalFor": 2,
    "goalAgainst": 3,
    "goalDifference": -1,
    "team": "BV Borussia"
  },
  {
    "played": 2,
    "won": 0,
    "drawn": 1,
    "lost": 1,
    "points": 1,
    "goalFor": 2,
    "goalAgainst": 5,
    "goalDifference": -3,
    "team": "Paris Saint-Germain FC"
  },
  {
    "played": 2,
    "won": 0,
    "drawn": 0,
    "lost": 2,
    "points": 0,
    "goalFor": 2,
    "goalAgainst": 4,
    "goalDifference": -2,
    "team": "FC Barcelona"
  },
  {
    "played": 2,
    "won": 0,
    "drawn": 0,
    "lost": 2,
    "points": 0,
    "goalFor": 0,
    "goalAgainst": 6,
    "goalDifference": -6,
    "team": "Arsenal FC"
  }
]